IDAMoles/__init__.py
idamoles-1.0.3.dist-info/licenses/LICENSE
idamoles-1.0.3.dist-info/METADATA
idamoles-1.0.3.dist-info/WHEEL
idamoles-1.0.3.dist-info/top_level.txt
idamoles-1.0.3.dist-info/RECORD
