Metadata-Version: 2.4
Name: IDAMoles
Version: 1.0.3
Summary: IDA Moles is a reverse analysis interface for IDA Pro 9.1. It controls decompilation, debugging, and other operations via standardized calls, returning POST-formatted results. It supports custom MCP server development to enhance reverse analysis efficiency and flexibility.
Home-page: http://moles.lyshark.com
Author: lyshark
Author-email: me@lyshark.com
License: MIT Licence
Platform: any
Classifier: Programming Language :: Python :: 3
Classifier: License :: OSI Approved :: MIT License
Classifier: Operating System :: OS Independent
Requires-Python: >=3.6.0
License-File: LICENSE
Dynamic: author
Dynamic: author-email
Dynamic: classifier
Dynamic: description
Dynamic: description-content-type
Dynamic: home-page
Dynamic: license
Dynamic: license-file
Dynamic: platform
Dynamic: requires-python
Dynamic: summary
